<node baseType="ArnoldShadingNode" edited="true" name="alSwitchColor" selected="true" type="ArnoldShadingNode">
  <port name="inputA" type="in">
    <metadata>
      <entry key="label" value="Input 0"/>
    </metadata>
  </port>
  <port name="inputA.r" type="in">
    <tags>
      <tag name="float or rgb or rgba or vector or point or point2"/>
    </tags>
  </port>
  <port name="inputA.g" type="in">
    <tags>
      <tag name="float or rgb or rgba or vector or point or point2"/>
    </tags>
  </port>
  <port name="inputA.b" type="in">
    <tags>
      <tag name="float or rgb or rgba or vector or point or point2"/>
    </tags>
  </port>
  <port name="inputB" type="in">
    <metadata>
      <entry key="label" value="Input 1"/>
    </metadata>
  </port>
  <port name="inputB.r" type="in">
    <tags>
      <tag name="float or rgb or rgba or vector or point or point2"/>
    </tags>
  </port>
  <port name="inputB.g" type="in">
    <tags>
      <tag name="float or rgb or rgba or vector or point or point2"/>
    </tags>
  </port>
  <port name="inputB.b" type="in">
    <tags>
      <tag name="float or rgb or rgba or vector or point or point2"/>
    </tags>
  </port>
  <port name="inputC" type="in">
    <metadata>
      <entry key="label" value="Input 2"/>
    </metadata>
  </port>
  <port name="inputC.r" type="in">
    <tags>
      <tag name="float or rgb or rgba or vector or point or point2"/>
    </tags>
  </port>
  <port name="inputC.g" type="in">
    <tags>
      <tag name="float or rgb or rgba or vector or point or point2"/>
    </tags>
  </port>
  <port name="inputC.b" type="in">
    <tags>
      <tag name="float or rgb or rgba or vector or point or point2"/>
    </tags>
  </port>
  <port name="inputD" type="in">
    <metadata>
      <entry key="label" value="Input 3"/>
    </metadata>
  </port>
  <port name="inputD.r" type="in">
    <tags>
      <tag name="float or rgb or rgba or vector or point or point2"/>
    </tags>
  </port>
  <port name="inputD.g" type="in">
    <tags>
      <tag name="float or rgb or rgba or vector or point or point2"/>
    </tags>
  </port>
  <port name="inputD.b" type="in">
    <tags>
      <tag name="float or rgb or rgba or vector or point or point2"/>
    </tags>
  </port>
  <port name="inputE" type="in">
    <metadata>
      <entry key="label" value="Input 4"/>
    </metadata>
  </port>
  <port name="inputE.r" type="in">
    <tags>
      <tag name="float or rgb or rgba or vector or point or point2"/>
    </tags>
  </port>
  <port name="inputE.g" type="in">
    <tags>
      <tag name="float or rgb or rgba or vector or point or point2"/>
    </tags>
  </port>
  <port name="inputE.b" type="in">
    <tags>
      <tag name="float or rgb or rgba or vector or point or point2"/>
    </tags>
  </port>
  <port name="inputF" type="in">
    <metadata>
      <entry key="label" value="Input 5"/>
    </metadata>
  </port>
  <port name="inputF.r" type="in">
    <tags>
      <tag name="float or rgb or rgba or vector or point or point2"/>
    </tags>
  </port>
  <port name="inputF.g" type="in">
    <tags>
      <tag name="float or rgb or rgba or vector or point or point2"/>
    </tags>
  </port>
  <port name="inputF.b" type="in">
    <tags>
      <tag name="float or rgb or rgba or vector or point or point2"/>
    </tags>
  </port>
  <port name="inputG" type="in">
    <metadata>
      <entry key="label" value="Input 6"/>
    </metadata>
  </port>
  <port name="inputG.r" type="in">
    <tags>
      <tag name="float or rgb or rgba or vector or point or point2"/>
    </tags>
  </port>
  <port name="inputG.g" type="in">
    <tags>
      <tag name="float or rgb or rgba or vector or point or point2"/>
    </tags>
  </port>
  <port name="inputG.b" type="in">
    <tags>
      <tag name="float or rgb or rgba or vector or point or point2"/>
    </tags>
  </port>
  <port name="inputH" type="in">
    <metadata>
      <entry key="label" value="Input 7"/>
    </metadata>
  </port>
  <port name="inputH.r" type="in">
    <tags>
      <tag name="float or rgb or rgba or vector or point or point2"/>
    </tags>
  </port>
  <port name="inputH.g" type="in">
    <tags>
      <tag name="float or rgb or rgba or vector or point or point2"/>
    </tags>
  </port>
  <port name="inputH.b" type="in">
    <tags>
      <tag name="float or rgb or rgba or vector or point or point2"/>
    </tags>
  </port>
  <port name="mix" type="in">
    <metadata>
      <entry key="label" value="mix"/>
    </metadata>
  </port>
  <port name="threshold" type="in">
    <metadata>
      <entry key="label" value="threshold"/>
    </metadata>
  </port>
  <port name="out" type="out">
    <tags>
      <tag name="rgb"/>
    </tags>
  </port>
  <port name="out.r" type="out">
    <tags>
      <tag name="float"/>
    </tags>
  </port>
  <port name="out.g" type="out">
    <tags>
      <tag name="float"/>
    </tags>
  </port>
  <port name="out.b" type="out">
    <tags>
      <tag name="float"/>
    </tags>
  </port>
  <group_parameter name="alSwitchColor">
    <string_parameter name="name" value="alSwitchColor"/>
    <string_parameter name="nodeType" value="alSwitchColor"/>
    <string_parameter name="__lastValue" value="pyh7tu337slgkq5whsdgayjmge3rqzbobkbw2bqv5wx5bjebwbc4False"/>
    <string_parameter name="__showHiddenParams" value="False"/>
    <group_parameter name="parameters">
      <group_parameter name="inputA">
        <number_parameter name="enable" value="0"/>
        <numberarray_parameter name="value" size="3" tupleSize="3">
          <number_parameter name="i0" value="0"/>
          <number_parameter name="i1" value="0"/>
          <number_parameter name="i2" value="0"/>
        </numberarray_parameter>
        <string_parameter name="type" value="FloatAttr"/>
      </group_parameter>
      <group_parameter name="inputB">
        <number_parameter name="enable" value="0"/>
        <numberarray_parameter name="value" size="3" tupleSize="3">
          <number_parameter name="i0" value="1"/>
          <number_parameter name="i1" value="1"/>
          <number_parameter name="i2" value="1"/>
        </numberarray_parameter>
        <string_parameter name="type" value="FloatAttr"/>
      </group_parameter>
      <group_parameter name="inputC">
        <number_parameter name="enable" value="0"/>
        <numberarray_parameter name="value" size="3" tupleSize="3">
          <number_parameter name="i0" value="1"/>
          <number_parameter name="i1" value="0"/>
          <number_parameter name="i2" value="0"/>
        </numberarray_parameter>
        <string_parameter name="type" value="FloatAttr"/>
      </group_parameter>
      <group_parameter name="inputD">
        <number_parameter name="enable" value="0"/>
        <numberarray_parameter name="value" size="3" tupleSize="3">
          <number_parameter name="i0" value="0"/>
          <number_parameter name="i1" value="1"/>
          <number_parameter name="i2" value="0"/>
        </numberarray_parameter>
        <string_parameter name="type" value="FloatAttr"/>
      </group_parameter>
      <group_parameter name="inputE">
        <number_parameter name="enable" value="0"/>
        <numberarray_parameter name="value" size="3" tupleSize="3">
          <number_parameter name="i0" value="0"/>
          <number_parameter name="i1" value="0"/>
          <number_parameter name="i2" value="1"/>
        </numberarray_parameter>
        <string_parameter name="type" value="FloatAttr"/>
      </group_parameter>
      <group_parameter name="inputF">
        <number_parameter name="enable" value="0"/>
        <numberarray_parameter name="value" size="3" tupleSize="3">
          <number_parameter name="i0" value="1"/>
          <number_parameter name="i1" value="1"/>
          <number_parameter name="i2" value="0"/>
        </numberarray_parameter>
        <string_parameter name="type" value="FloatAttr"/>
      </group_parameter>
      <group_parameter name="inputG">
        <number_parameter name="enable" value="0"/>
        <numberarray_parameter name="value" size="3" tupleSize="3">
          <number_parameter name="i0" value="1"/>
          <number_parameter name="i1" value="0"/>
          <number_parameter name="i2" value="1"/>
        </numberarray_parameter>
        <string_parameter name="type" value="FloatAttr"/>
      </group_parameter>
      <group_parameter name="inputH">
        <number_parameter name="enable" value="0"/>
        <numberarray_parameter name="value" size="3" tupleSize="3">
          <number_parameter name="i0" value="0"/>
          <number_parameter name="i1" value="1"/>
          <number_parameter name="i2" value="1"/>
        </numberarray_parameter>
        <string_parameter name="type" value="FloatAttr"/>
      </group_parameter>
      <group_parameter name="mix">
        <number_parameter name="enable" value="0"/>
        <number_parameter name="value" value="1"/>
        <string_parameter name="type" value="FloatAttr"/>
      </group_parameter>
      <group_parameter name="threshold">
        <number_parameter name="enable" value="0"/>
        <number_parameter name="value" value="0.5"/>
        <string_parameter name="type" value="FloatAttr"/>
      </group_parameter>
      <group_parameter name="__unused"/>
    </group_parameter>
    <group_parameter name="publicInterface">
      <string_parameter name="namePrefix" value=""/>
      <string_parameter name="pagePrefix" value=""/>
      <string_parameter name="nameRegExFind" value=""/>
      <string_parameter name="nameRegExReplace" value=""/>
      <string_parameter name="pageRegExFind" value=""/>
      <string_parameter name="pageRegExReplace" value=""/>
    </group_parameter>
    <string_parameter name="forceRefresh" value=""/>
  </group_parameter>
</node>
