<node baseType="PrmanShadingNode" name="PxrRamp" selected="true" type="PrmanShadingNode">
    <port name="positions" type="in">
    <tags>
        <tag name="float"/>
    </tags>
    <metadata>
        <entry key="label" value="Positions"/>
    </metadata>
    </port>
    <port name="colors" type="in">
    <tags>
        <tag name="color"/>
    </tags>
    <metadata>
        <entry key="label" value="Colors"/>
    </metadata>
    </port>
    <port name="splineMap" type="in">
    <tags>
        <tag name="float"/>
    </tags>
    <metadata>
        <entry key="label" value="Spline Map"/>
    </metadata>
    </port>
    <port name="manifold" type="in">
    <tags>
        <tag name="manifold"/>
        <tag name="struct"/>
    </tags>
    <metadata>
        <entry key="label" value="Manifold"/>
    </metadata>
    </port>
    <port name="resultRGB" type="out">
    <tags>
        <tag name="color"/>
        <tag name="normal"/>
        <tag name="point"/>
        <tag name="vector"/>
    </tags>
    </port>
    <port name="resultR" type="out">
    <tags>
        <tag name="float"/>
    </tags>
    </port>
    <port name="resultG" type="out">
    <tags>
        <tag name="float"/>
    </tags>
    </port>
    <port name="resultB" type="out">
    <tags>
        <tag name="float"/>
    </tags>
    </port>
    <group_parameter name="PxrRamp">
    <string_parameter name="name" value="PxrRamp"/>
    <string_parameter name="nodeType" value="PxrRamp"/>
    <string_parameter name="__lastValue" value="34gnic6nw55bkigq66y2eoyuwycgpzbrkgccf2vmbu3zuugyr6byFalse"/>
    <string_parameter name="__showHiddenParams" value="False"/>
    <group_parameter name="parameters">
        <group_parameter name="rampType">
        <number_parameter name="enable" value="0"/>
        <number_parameter name="value" value="0"/>
        <string_parameter name="type" value="IntAttr"/>
        </group_parameter>
        <group_parameter name="tile">
        <number_parameter name="enable" value="0"/>
        <number_parameter name="value" value="0"/>
        <string_parameter name="type" value="IntAttr"/>
        </group_parameter>
        <group_parameter name="positions">
        <number_parameter name="enable" value="0"/>
        <number_parameter name="isDynamicArray" value="1"/>
        <numberarray_parameter name="value" size="1" tupleSize="1">
        </numberarray_parameter>
        <string_parameter name="type" value="FloatAttr"/>
        </group_parameter>
        <group_parameter name="colors">
        <number_parameter name="enable" value="0"/>
        <number_parameter name="isDynamicArray" value="1"/>
        <numberarray_parameter name="value" size="3" tupleSize="3">
        </numberarray_parameter>
        <string_parameter name="type" value="FloatAttr"/>
        </group_parameter>
        <group_parameter name="reverse">
        <number_parameter name="enable" value="0"/>
        <number_parameter name="value" value="0"/>
        <string_parameter name="type" value="IntAttr"/>
        </group_parameter>
        <group_parameter name="basis">
        <number_parameter name="enable" value="0"/>
        <number_parameter name="value" value="4"/>
        <string_parameter name="type" value="IntAttr"/>
        </group_parameter>
        <group_parameter name="splineMap">
        <number_parameter name="enable" value="0"/>
        <number_parameter name="value" value="0"/>
        <string_parameter name="type" value="FloatAttr"/>
        </group_parameter>
        <group_parameter name="randomSource">
        <number_parameter name="enable" value="0"/>
        <number_parameter name="value" value="0"/>
        <string_parameter name="type" value="IntAttr"/>
        </group_parameter>
        <group_parameter name="randomSeed">
        <number_parameter name="enable" value="0"/>
        <number_parameter name="value" value="0"/>
        <string_parameter name="type" value="FloatAttr"/>
        </group_parameter>
        <group_parameter name="manifold">
        <number_parameter name="enable" value="0"/>
        <string_parameter name="value" value=""/>
        <string_parameter name="type" value="StringAttr"/>
        </group_parameter>
        <group_parameter name="__unused"/>
    </group_parameter>
    <group_parameter name="publicInterface">
        <string_parameter name="namePrefix" value=""/>
        <string_parameter name="pagePrefix" value=""/>
        <string_parameter name="nameRegExFind" value=""/>
        <string_parameter name="nameRegExReplace" value=""/>
        <string_parameter name="pageRegExFind" value=""/>
        <string_parameter name="pageRegExReplace" value=""/>
    </group_parameter>
    <string_parameter name="forceRefresh" value=""/>
    </group_parameter>
</node>
